Metadata-Version: 2.1
Name: dsp-basicalgorithms
Version: 0.122
Summary: Basic Dsp algorithms and Filter Design
Home-page: UNKNOWN
Author: Shivaprasad Rao
Author-email: shivarao101@gmail.com
License: UNKNOWN
Platform: UNKNOWN
Classifier: Programming Language :: Python :: 3
Classifier: License :: OSI Approved :: MIT License
Classifier: Operating System :: OS Independent
Requires-Python: >=3.6
